html_alg_lib/__init__.py
html_alg_lib/base_funcs.py
html_alg_lib/call_api.py
html_alg_lib/simplify.py
html_alg_lib/view_result.py
html_alg_lib/html_simplify/__init__.py
html_alg_lib/html_simplify/base_operations.py
html_alg_lib/html_simplify/cfg_reader.py
html_alg_lib/html_simplify/dom_framework.py
html_alg_lib/html_simplify/feature.py
html_alg_lib/html_simplify/html2text.py
html_alg_lib/html_simplify/html_utils.py
html_alg_lib/html_simplify/pipeline.py
html_alg_lib/html_simplify/processor.py
html_alg_lib/html_simplify/assets/default_cls_simplify_cfg.jsonc
html_alg_lib/html_simplify/assets/default_general_simplify_cfg.jsonc
html_alg_lib/html_simplify/assets/default_label_simplify_cfg.jsonc
html_alg_lib/html_simplify/assets/tags_attr.jsonl
html_alg_lib/html_simplify/processes/__init__.py
html_alg_lib/html_simplify/processes/alg_readable.py
html_alg_lib/html_simplify/processes/merge_tags.py
html_alg_lib/html_simplify/processes/pre_normalize.py
html_alg_lib/html_simplify/processes/remove_tags.py
html_alg_lib/html_simplify/processes/unwrap_tags.py
html_alg_lib-2.0.2.dist-info/licenses/LICENCE
html_alg_lib-2.0.2.dist-info/METADATA
html_alg_lib-2.0.2.dist-info/WHEEL
html_alg_lib-2.0.2.dist-info/top_level.txt
html_alg_lib-2.0.2.dist-info/RECORD
