Metadata-Version: 2.4
Name: html_alg_lib
Version: 2.0.2
Author: Qiu Jiantao
Author-email: qiujiantao@pjlab.org.cn
License: MIT
Requires-Python: >=3.10
License-File: LICENCE
Requires-Dist: lxml>=5.3.0
Requires-Dist: beautifulsoup4>=4.12.2
Requires-Dist: commentjson==0.9.0
Provides-Extra: full
Requires-Dist: chardet==5.2.0; extra == "full"
Requires-Dist: openai==1.76.0; extra == "full"
Requires-Dist: Requests==2.32.3; extra == "full"
Requires-Dist: aiohttp==3.8.5; extra == "full"
Requires-Dist: jieba==0.42.1; extra == "full"
Requires-Dist: ltp==4.2.14; extra == "full"
Requires-Dist: rouge_score==0.1.2; extra == "full"
Dynamic: author
Dynamic: author-email
Dynamic: description
Dynamic: description-content-type
Dynamic: license
Dynamic: license-file
Dynamic: provides-extra
Dynamic: requires-dist
Dynamic: requires-python
